py_seedlings/__init__.py
py_seedlings/py_seedlings.py
py_seedlings/utils.py
py_seedlings-0.12.0.dist-info/LICENSE
py_seedlings-0.12.0.dist-info/METADATA
py_seedlings-0.12.0.dist-info/WHEEL
py_seedlings-0.12.0.dist-info/top_level.txt
py_seedlings-0.12.0.dist-info/RECORD
