Metadata-Version: 2.1
Name: py-seedlings
Version: 0.12.0
Summary: helpful python starter functions for various repository use
Home-page: https://pypi.org/project/py-seedlings/
Author: James Kabbes
Author-email: james.kabbes@gmail.com
Project-URL: GitHub, https://github.com/jameskabbes/py_starter
Project-URL: Documentation, https://jameskabbes.github.io/py_starter
Classifier: Programming Language :: Python :: 3
Classifier: License :: OSI Approved :: MIT License
Classifier: Operating System :: OS Independent
Requires-Python: >=3.6
License-File: LICENSE
